brilliant_monocle_driver/__init__.py
brilliant_monocle_driver/batched.py
brilliant_monocle_driver/line_reader.py
brilliant_monocle_driver-0.1.3.dist-info/LICENSE
brilliant_monocle_driver-0.1.3.dist-info/METADATA
brilliant_monocle_driver-0.1.3.dist-info/WHEEL
brilliant_monocle_driver-0.1.3.dist-info/top_level.txt
brilliant_monocle_driver-0.1.3.dist-info/RECORD
