Metadata-Version: 2.1
Name: brilliant-monocle-driver
Version: 0.1.3
Summary: A driver to connect to and control a Brilliant Labs Monocle peripheral
Author-email: "Mark T. Tomczak" <iam@fixermark.com>
License: ISC Licence
Project-URL: repository, https://github.com/fixermark/brilliant-monocle-driver-python
Project-URL: changelog, https://github.com/fixermark/brilliant-monocle-driver-python/blob/main/Changelog.md
Keywords: Brilliant Labs,AR,Bluetooth
Requires-Python: >=3.9
License-File: LICENSE
Requires-Dist: bleak (>=0.20.1)
